hub20/__init__.py
hub20/api/__init__.py
hub20/api/celery.py
hub20/api/middleware.py
hub20/api/routing.py
hub20/api/settings.py
hub20/api/urls.py
hub20/api/wsgi.py
hub20/apps/__init__.py
hub20/apps/blockchain/__init__.py
hub20/apps/blockchain/app_settings.py
hub20/apps/blockchain/apps.py
hub20/apps/blockchain/choices.py
hub20/apps/blockchain/constants.py
hub20/apps/blockchain/fields.py
hub20/apps/blockchain/models.py
hub20/apps/blockchain/serializers.py
hub20/apps/blockchain/validators.py
hub20/apps/blockchain/factories/__init__.py
hub20/apps/blockchain/factories/base.py
hub20/apps/blockchain/factories/providers.py
hub20/apps/blockchain/management/__init__.py
hub20/apps/blockchain/management/commands/__init__.py
hub20/apps/blockchain/management/commands/sync_blockchain.py
hub20/apps/blockchain/migrations/0001_initial.py
hub20/apps/blockchain/migrations/__init__.py
hub20/apps/core/__init__.py
hub20/apps/core/admin.py
hub20/apps/core/api.py
hub20/apps/core/app_settings.py
hub20/apps/core/apps.py
hub20/apps/core/choices.py
hub20/apps/core/consumers.py
hub20/apps/core/handlers.py
hub20/apps/core/serializers.py
hub20/apps/core/settings.py
hub20/apps/core/signals.py
hub20/apps/core/tasks.py
hub20/apps/core/views.py
hub20/apps/core/factories/__init__.py
hub20/apps/core/factories/accounting.py
hub20/apps/core/factories/base.py
hub20/apps/core/factories/payments.py
hub20/apps/core/factories/store.py
hub20/apps/core/factories/transfers.py
hub20/apps/core/management/__init__.py
hub20/apps/core/management/commands/__init__.py
hub20/apps/core/management/commands/track_pending_payments.py
hub20/apps/core/migrations/0001_initial.py
hub20/apps/core/migrations/__init__.py
hub20/apps/core/models/__init__.py
hub20/apps/core/models/accounting.py
hub20/apps/core/models/payments.py
hub20/apps/core/models/store.py
hub20/apps/core/models/transfers.py
hub20/apps/core/tests/__init__.py
hub20/apps/core/tests/base.py
hub20/apps/core/tests/test_consumers.py
hub20/apps/core/tests/test_models.py
hub20-0.1.3.dist-info/LICENSE
hub20-0.1.3.dist-info/METADATA
hub20-0.1.3.dist-info/WHEEL
hub20-0.1.3.dist-info/top_level.txt
hub20-0.1.3.dist-info/RECORD
