Metadata-Version: 2.1
Name: hub20
Version: 0.1.3
Summary: ## Welcome to Hub20 
Requires-Dist: attributedict
Requires-Dist: celery
Requires-Dist: channels
Requires-Dist: channels-redis
Requires-Dist: django
Requires-Dist: django-allauth
Requires-Dist: django-cors-headers
Requires-Dist: django-ipware
Requires-Dist: django-model-utils
Requires-Dist: django-pdb
Requires-Dist: django-redis
Requires-Dist: djangorestframework
Requires-Dist: django-rest-auth
Requires-Dist: django-smtp-ssl
Requires-Dist: django-money
Requires-Dist: ethereum
Requires-Dist: eth-abi
Requires-Dist: ethtoken
Requires-Dist: mypy-extensions
Requires-Dist: psycopg2-binary
Requires-Dist: pycoingecko
Requires-Dist: pycryptodome
Requires-Dist: pyjwt
Requires-Dist: raiden-contracts
Requires-Dist: uvicorn
Requires-Dist: web3 (<6.0.0,>=5.4.0)
